panw_utils/__init__.py
panw_utils/get_panw_api_key.py
panw_utils/get_panw_config.py
panw_utils/get_panw_firewalls.py
panw_utils/get_panw_interfaces.py
panw_utils/panw_utils.py
panw_utils/run_panw_cmd.py
panw_utils-0.7.10.dist-info/AUTHORS.rst
panw_utils-0.7.10.dist-info/LICENSE
panw_utils-0.7.10.dist-info/METADATA
panw_utils-0.7.10.dist-info/WHEEL
panw_utils-0.7.10.dist-info/entry_points.txt
panw_utils-0.7.10.dist-info/top_level.txt
panw_utils-0.7.10.dist-info/RECORD
