Metadata-Version: 2.1
Name: panw-utils
Version: 0.7.10
Summary: Palo Alto Networks Utilities
Home-page: https://github.com/dapacruz/panw-utils
Author: David Paul Cruz
Author-email: davidcruz72@gmail.com
License: MIT license
Keywords: panw_utils
Platform: UNKNOWN
Classifier: Development Status :: 2 - Pre-Alpha
Classifier: Intended Audience :: System Administrators
Classifier: License :: OSI Approved :: MIT License
Classifier: Natural Language :: English
Classifier: Programming Language :: Python :: 3.6
Classifier: Programming Language :: Python :: 3.7
Requires-Dist: cryptography (==3.1)
Requires-Dist: netmiko (==3.3.0)
Requires-Dist: paramiko (==2.7.2)
Requires-Dist: lxml (==4.5.2)
